collate_dbt_artifacts_parser/__init__.py
collate_dbt_artifacts_parser/parser.py
collate_dbt_artifacts_parser/utils.py
collate_dbt_artifacts_parser/parsers/__init__.py
collate_dbt_artifacts_parser/parsers/base.py
collate_dbt_artifacts_parser/parsers/utils.py
collate_dbt_artifacts_parser/parsers/version_map.py
collate_dbt_artifacts_parser/parsers/catalog/__init__.py
collate_dbt_artifacts_parser/parsers/catalog/catalog_cloud.py
collate_dbt_artifacts_parser/parsers/catalog/catalog_cloud_v1.py
collate_dbt_artifacts_parser/parsers/catalog/catalog_cloud_v2.py
collate_dbt_artifacts_parser/parsers/catalog/catalog_v1.py
collate_dbt_artifacts_parser/parsers/manifest/__init__.py
collate_dbt_artifacts_parser/parsers/manifest/manifest_cloud.py
collate_dbt_artifacts_parser/parsers/manifest/manifest_cloud_v1.py
collate_dbt_artifacts_parser/parsers/manifest/manifest_cloud_v2.py
collate_dbt_artifacts_parser/parsers/manifest/manifest_v1.py
collate_dbt_artifacts_parser/parsers/manifest/manifest_v10.py
collate_dbt_artifacts_parser/parsers/manifest/manifest_v11.py
collate_dbt_artifacts_parser/parsers/manifest/manifest_v12.py
collate_dbt_artifacts_parser/parsers/manifest/manifest_v2.py
collate_dbt_artifacts_parser/parsers/manifest/manifest_v3.py
collate_dbt_artifacts_parser/parsers/manifest/manifest_v4.py
collate_dbt_artifacts_parser/parsers/manifest/manifest_v5.py
collate_dbt_artifacts_parser/parsers/manifest/manifest_v6.py
collate_dbt_artifacts_parser/parsers/manifest/manifest_v7.py
collate_dbt_artifacts_parser/parsers/manifest/manifest_v8.py
collate_dbt_artifacts_parser/parsers/manifest/manifest_v9.py
collate_dbt_artifacts_parser/parsers/run_results/__init__.py
collate_dbt_artifacts_parser/parsers/run_results/run_results_cloud.py
collate_dbt_artifacts_parser/parsers/run_results/run_results_cloud_v1.py
collate_dbt_artifacts_parser/parsers/run_results/run_results_cloud_v2.py
collate_dbt_artifacts_parser/parsers/run_results/run_results_v1.py
collate_dbt_artifacts_parser-0.1.3.dist-info/METADATA
collate_dbt_artifacts_parser-0.1.3.dist-info/WHEEL
collate_dbt_artifacts_parser-0.1.3.dist-info/licenses/LICENSE
collate_dbt_artifacts_parser-0.1.3.dist-info/RECORD
