Metadata-Version: 2.4
Name: collate-dbt-artifacts-parser
Version: 0.1.3
Summary: A dbt artifacts parser in python
Project-URL: Home, https://github.com/open-metadata/collate-dbt-artifacts-parser
Author: open-metadata
License:                                  Apache License
License-File: LICENSE
Classifier: Development Status :: 4 - Beta
Classifier: Intended Audience :: Information Technology
Classifier: Intended Audience :: System Administrators
Classifier: License :: OSI Approved :: Apache Software License
Classifier: Operating System :: OS Independent
Classifier: Programming Language :: Python
Classifier: Programming Language :: Python :: 3
Classifier: Programming Language :: Python :: 3 :: Only
Classifier: Programming Language :: Python :: 3.8
Classifier: Programming Language :: Python :: 3.9
Classifier: Programming Language :: Python :: 3.10
Classifier: Programming Language :: Python :: 3.11
Classifier: Programming Language :: Python :: 3.12
Classifier: Topic :: Software Development :: Libraries
Classifier: Topic :: Software Development :: Libraries :: Python Modules
Classifier: Typing :: Typed
Requires-Python: >=3.8.0
Requires-Dist: pydantic<3.0,>=2.0
Provides-Extra: dev
Requires-Dist: black==24.8.0; extra == 'dev'
Requires-Dist: build==1.2.2; extra == 'dev'
Requires-Dist: datamodel-code-generator<0.30,>=0.20; extra == 'dev'
Requires-Dist: flake8<4.0.0,>=3.8.3; extra == 'dev'
Requires-Dist: isort<6.0.0,>=5.0.6; extra == 'dev'
Requires-Dist: mypy==1.14.1; extra == 'dev'
Requires-Dist: pdoc3>=0.9.2; extra == 'dev'
Requires-Dist: pre-commit>=2.15.0; extra == 'dev'
Requires-Dist: pylint>=2.12.0; extra == 'dev'
Requires-Dist: pyyaml>=5.3; extra == 'dev'
Provides-Extra: test
Requires-Dist: pytest<9.0.0,>=6.2.4; extra == 'test'
